wecoai/__init__.py
wecoai-0.0.1.dist-info/METADATA
wecoai-0.0.1.dist-info/WHEEL
wecoai-0.0.1.dist-info/top_level.txt
wecoai-0.0.1.dist-info/RECORD
