Metadata-Version: 2.1
Name: wecoai
Version: 0.0.1
Summary: Python package for using Weco's service
Author: Yuxiang Wu
Author-email: Yuxiang Wu <yuxiang@weco.ai>
Classifier: Programming Language :: Python :: 3
Classifier: License :: OSI Approved :: MIT License
Classifier: Operating System :: OS Independent
Requires-Python: >=3.8
